{"version": 0.6, "generator": "Overpass API 0.7.59.4 36d058c8", "osm3s": {"timestamp_osm_base": "2023-03-07T10:53:49Z", "copyright": "The data included in this document is from www.openstreetmap.org. The data is made available under ODbL."}, "elements": [{"type": "node", "id": 1438199502, "lat": 50.8766763, "lon": 4.7056076}, {"type": "node", "id": 1490307247, "lat": 50.8766972, "lon": 4.7057372}, {"type": "node", "id": 1490307250, "lat": 50.8766448, "lon": 4.7056468}, {"type": "node", "id": 6265887588, "lat": 50.8752208, "lon": 4.7034119}, {"type": "node", "id": 6265887638, "lat": 50.8767024, "lon": 4.7056533}, {"type": "node", "id": 6265888544, "lat": 50.876705, "lon": 4.705726}, {"type": "node", "id": 6265888882, "lat": 50.8752066, "lon": 4.7033761}, {"type": "node", "id": 6265889582, "lat": 50.8751733, "lon": 4.7034082}, {"type": "node", "id": 6265889887, "lat": 50.8751874, "lon": 4.7034446}, {"type": "node", "id": 6265890516, "lat": 50.8767255, "lon": 4.7056936}, {"type": "way", "id": 135746786, "nodes": [6265888544, 1490307247, 1490307250, 1438199502, 6265887638, 6265890516, 6265888544], "tags": {"building": "service", "power": "substation", "source:geometry": "Informatie Vlaanderen - GRB", "source:geometry:date": "2011-12-20", "source:geometry:lbltype": "bijgebouw", "source:geometry:ref": "Gbg/2874040", "substation": "minor_distribution"}}, {"type": "way", "id": 669129063, "nodes": [6265889887, 6265889582, 6265888882, 6265887588, 6265889887], "tags": {"building": "yes", "power": "substation", "source:geometry": "Informatie Vlaanderen - GRB", "source:geometry:date": "2017-10-11", "source:geometry:ref": "Gbg/2874041", "substation": "minor_distribution"}}]}