{"version": 0.6, "generator": "Overpass API 0.7.59.4 36d058c8", "osm3s": {"timestamp_osm_base": "2023-03-07T10:52:54Z", "copyright": "The data included in this document is from www.openstreetmap.org. The data is made available under ODbL."}, "elements": [{"type": "node", "id": 2149475366, "lat": 44.1757391, "lon": 24.5091748}, {"type": "node", "id": 2149475367, "lat": 44.1760074, "lon": 24.509752}, {"type": "node", "id": 2149475368, "lat": 44.1766203, "lon": 24.5092473}, {"type": "node", "id": 2149475373, "lat": 44.1769229, "lon": 24.5078649}, {"type": "node", "id": 2149475375, "lat": 44.177291, "lon": 24.5085697}, {"type": "node", "id": 2149475376, "lat": 44.1774269, "lon": 24.5120529}, {"type": "node", "id": 2149475378, "lat": 44.1776023, "lon": 24.5112227}, {"type": "node", "id": 2149475380, "lat": 44.1777541, "lon": 24.5110599}, {"type": "node", "id": 2149475381, "lat": 44.1778256, "lon": 24.5115793}, {"type": "way", "id": 204969810, "nodes": [2149475373, 2149475375, 2149475368, 2149475380, 2149475378, 2149475381, 2149475376, 2149475367, 2149475366, 2149475373], "tags": {"name": "Dr\u0103g\u0103ne\u0219ti-Olt", "operator": "TEL", "power": "substation", "source": "Bing", "substation": "transmission", "voltage": "400000;110000"}}]}