[{"place_id": 98351937, "licence": "Data \u00a9 OpenStreetMap contributors, ODbL 1.0. https://osm.org/copyright", "osm_type": "node", "osm_id": 9831956834, "boundingbox": ["45.6138373", "45.6238373", "25.6486036", "25.6586036"], "lat": "45.6188373", "lon": "25.6536036", "display_name": "D\u00e2rste, Strada G\u0103rii D\u00e2rste, Noua-D\u00e2rste, Brasov, Zona Metropolitan\u0103 Bra\u0219ov, Bra\u0219ov, 500299, Romania", "class": "railway", "type": "station", "importance": 0.10000999999999996, "icon": "https://nominatim.openstreetmap.org/ui/mapicons/transport_train_station2.p.20.png", "geojson": {"type": "Point", "coordinates": [25.6536036, 45.6188373]}}, {"place_id": 168534228, "licence": "Data \u00a9 OpenStreetMap contributors, ODbL 1.0. https://osm.org/copyright", "osm_type": "way", "osm_id": 241896387, "boundingbox": ["45.6186638", "45.6190234", "25.6534096", "25.6537901"], "lat": "45.61884365", "lon": "25.653599814263437", "display_name": "D\u00e2rste, Strada Timi\u0219ul Sec (Centura Bra\u0219ovului), Brasov, Zona Metropolitan\u0103 Bra\u0219ov, Bra\u0219ov, 500299, Romania", "class": "building", "type": "train_station", "importance": 0.10000999999999996, "geojson": {"type": "Polygon", "coordinates": [[[25.6534096, 45.6189675], [25.653638, 45.6186638], [25.6537901, 45.6187198], [25.6535616, 45.6190234], [25.6534096, 45.6189675]]]}}, {"place_id": 101877888, "licence": "Data \u00a9 OpenStreetMap contributors, ODbL 1.0. https://osm.org/copyright", "osm_type": "node", "osm_id": 10151493630, "boundingbox": ["45.6186084", "45.6187084", "25.6502509", "25.6503509"], "lat": "45.6186584", "lon": "25.6503009", "display_name": "easybox, Calea Bucure\u0219ti, Noua-D\u00e2rste, Brasov, Zona Metropolitan\u0103 Bra\u0219ov, Bra\u0219ov, 500299, Romania", "class": "amenity", "type": "parcel_locker", "importance": 0.10000999999999996, "geojson": {"type": "Point", "coordinates": [25.6503009, 45.6186584]}}, {"place_id": 43969422, "licence": "Data \u00a9 OpenStreetMap contributors, ODbL 1.0. https://osm.org/copyright", "osm_type": "node", "osm_id": 3709600097, "boundingbox": ["45.6175761", "45.6176761", "25.6518142", "25.6519142"], "lat": "45.6176261", "lon": "25.6518642", "display_name": "Aurora, Calea Bucure\u0219ti, Noua-D\u00e2rste, Brasov, Zona Metropolitan\u0103 Bra\u0219ov, Bra\u0219ov, 500299, Romania", "class": "highway", "type": "bus_stop", "importance": 0.10000999999999996, "icon": "https://nominatim.openstreetmap.org/ui/mapicons/transport_bus_stop2.p.20.png", "geojson": {"type": "Point", "coordinates": [25.6518642, 45.6176261]}}, {"place_id": 43872345, "licence": "Data \u00a9 OpenStreetMap contributors, ODbL 1.0. https://osm.org/copyright", "osm_type": "node", "osm_id": 3709600098, "boundingbox": ["45.6172452", "45.6173452", "25.6518439", "25.6519439"], "lat": "45.6172952", "lon": "25.6518939", "display_name": "Aurora, Calea Bucure\u0219ti, Noua-D\u00e2rste, Brasov, Zona Metropolitan\u0103 Bra\u0219ov, Bra\u0219ov, 500299, Romania", "class": "highway", "type": "bus_stop", "importance": 0.10000999999999996, "icon": "https://nominatim.openstreetmap.org/ui/mapicons/transport_bus_stop2.p.20.png", "geojson": {"type": "Point", "coordinates": [25.6518939, 45.6172952]}}]