{"version": 0.6, "generator": "Overpass API 0.7.59.4 36d058c8", "osm3s": {"timestamp_osm_base": "2023-03-07T10:48:53Z", "copyright": "The data included in this document is from www.openstreetmap.org. The data is made available under ODbL."}, "elements": [{"type": "node", "id": 1718987953, "lat": 47.8619374, "lon": 13.0579544}, {"type": "node", "id": 1718987956, "lat": 47.8619564, "lon": 13.0578941}, {"type": "node", "id": 1718987958, "lat": 47.8619663, "lon": 13.0579747}, {"type": "node", "id": 1718987966, "lat": 47.8619853, "lon": 13.0579145}, {"type": "node", "id": 2354517762, "lat": 47.8674746, "lon": 13.0627877}, {"type": "node", "id": 2354517763, "lat": 47.8674803, "lon": 13.0628538}, {"type": "node", "id": 2354517765, "lat": 47.8675176, "lon": 13.0627795}, {"type": "node", "id": 2354517766, "lat": 47.8675204, "lon": 13.0628114, "tags": {"power": "terminal"}}, {"type": "node", "id": 2354517767, "lat": 47.8675233, "lon": 13.0628456}, {"type": "node", "id": 2520709713, "lat": 47.868035, "lon": 13.0701623}, {"type": "node", "id": 2520709716, "lat": 47.8680596, "lon": 13.0702258}, {"type": "node", "id": 2520709719, "lat": 47.8680644, "lon": 13.0702017, "tags": {"power": "terminal"}}, {"type": "node", "id": 3226557034, "lat": 47.8598419, "lon": 13.061924}, {"type": "node", "id": 3226557042, "lat": 47.8598841, "lon": 13.0619609}, {"type": "node", "id": 3226557163, "lat": 47.8598636, "lon": 13.0618686}, {"type": "node", "id": 3226557202, "lat": 47.8599059, "lon": 13.0619053}, {"type": "node", "id": 4367831190, "lat": 47.8576459, "lon": 13.0586534}, {"type": "node", "id": 4367831191, "lat": 47.8576513, "lon": 13.0587285}, {"type": "node", "id": 4367831192, "lat": 47.8576821, "lon": 13.0586476}, {"type": "node", "id": 4367831193, "lat": 47.8576875, "lon": 13.0587227}, {"type": "node", "id": 4384880034, "lat": 47.8680253, "lon": 13.0702105}, {"type": "node", "id": 4384880039, "lat": 47.8680693, "lon": 13.0701775}, {"type": "node", "id": 4385368638, "lat": 47.8581635, "lon": 13.0643638}, {"type": "node", "id": 4385368639, "lat": 47.8581871, "lon": 13.0643349}, {"type": "node", "id": 4385368640, "lat": 47.8582042, "lon": 13.0643657}, {"type": "node", "id": 4385368641, "lat": 47.8581806, "lon": 13.0643947}, {"type": "node", "id": 4403939881, "lat": 47.8532811, "lon": 13.0562241}, {"type": "node", "id": 4403939882, "lat": 47.8533105, "lon": 13.0561924}, {"type": "node", "id": 4403939883, "lat": 47.8532958, "lon": 13.0562082}, {"type": "node", "id": 4403939884, "lat": 47.8533, "lon": 13.0562629}, {"type": "node", "id": 4403939885, "lat": 47.8533294, "lon": 13.0562312}, {"type": "way", "id": 159789295, "nodes": [1718987956, 1718987953, 1718987958, 1718987966, 1718987956], "tags": {"frequency": "50", "height": "4", "location": "indoor", "man_made": "street_cabinet", "operator": "Salzburg Netz", "power": "substation", "ref": "Elixhausen Aubergsiedlung", "street_cabinet": "power", "substation": "minor_distribution", "voltage": "30000"}}, {"type": "way", "id": 226685772, "nodes": [2354517765, 2354517762, 2354517763, 2354517767, 2354517766, 2354517765], "tags": {"building": "transformer_tower", "frequency": "50", "location": "indoor", "operator": "Salzburg Netz", "power": "substation", "ref": "Elixhausen Weichenberg", "substation": "minor_distribution", "voltage": "30000"}}, {"type": "way", "id": 244797262, "nodes": [2520709719, 2520709716, 4384880034, 2520709713, 4384880039, 2520709719], "tags": {"building": "transformer_tower", "frequency": "50", "height": "9", "location": "indoor", "operator": "Salzburg Netz", "power": "substation", "ref": "Elixhausen Gmachl", "substation": "minor_distribution", "voltage": "30000"}}, {"type": "way", "id": 316532811, "nodes": [3226557163, 3226557034, 3226557042, 3226557202, 3226557163], "tags": {"building": "transformer_tower", "frequency": "50", "location": "indoor", "operator": "Salzburg AG", "power": "substation", "ref": "Elixhausen Sachsenheimsiedlung", "substation": "minor_distribution", "voltage": "30000"}}, {"type": "way", "id": 439155469, "nodes": [4367831190, 4367831192, 4367831193, 4367831191, 4367831190], "tags": {"frequency": "50", "location": "indoor", "man_made": "street_cabinet", "operator": "Salzburg Netz", "power": "substation", "ref": "Auberg", "street_cabinet": "power", "substation": "minor_distribution", "voltage": "30000"}}, {"type": "way", "id": 440760904, "nodes": [4385368638, 4385368639, 4385368640, 4385368641, 4385368638], "tags": {"building": "transformer_tower", "frequency": "50", "location": "indoor", "operator": "Salzburg Netz", "power": "substation", "ref": "Elixhausen Katzmoos", "substation": "minor_distribution", "voltage": "30000"}}, {"type": "way", "id": 442732449, "nodes": [4403939881, 4403939883, 4403939882, 4403939885, 4403939884, 4403939881], "tags": {"building": "transformer_tower", "frequency": "50", "height": "8", "location": "indoor", "operator": "Salzburg Netz", "power": "substation", "ref": "Bergheim Aubergsiedlung", "substation": "minor_distribution", "voltage": "30000"}}]}