[{"place_id": 12314304, "licence": "Data \u00a9 OpenStreetMap contributors, ODbL 1.0. https://osm.org/copyright", "osm_type": "node", "osm_id": 1253155251, "boundingbox": ["51.6726159", "51.7126159", "7.920585", "7.960585"], "lat": "51.6926159", "lon": "7.940585", "display_name": "Uentrop, Hamm, North Rhine-Westphalia, Germany", "class": "place", "type": "suburb", "importance": 0.40454884777787203, "icon": "https://nominatim.openstreetmap.org/ui/mapicons/poi_place_village.p.20.png", "geojson": {"type": "Point", "coordinates": [7.940585, 51.6926159]}}, {"place_id": 25135937, "licence": "Data \u00a9 OpenStreetMap contributors, ODbL 1.0. https://osm.org/copyright", "osm_type": "node", "osm_id": 2693018832, "boundingbox": ["51.3826517", "51.4226517", "8.0692885", "8.1092885"], "lat": "51.4026517", "lon": "8.0892885", "display_name": "Uentrop, Arnsberg, Hochsauerlandkreis, North Rhine-Westphalia, 59821, Germany", "class": "place", "type": "village", "importance": 0.385, "icon": "https://nominatim.openstreetmap.org/ui/mapicons/poi_place_village.p.20.png", "geojson": {"type": "Point", "coordinates": [8.0892885, 51.4026517]}}, {"place_id": 343148671, "licence": "Data \u00a9 OpenStreetMap contributors, ODbL 1.0. https://osm.org/copyright", "osm_type": "way", "osm_id": 1094334661, "boundingbox": ["51.1187472", "51.1261323", "8.2400364", "8.2528377"], "lat": "51.1229941", "lon": "8.2468059", "display_name": "Uentrop, Wulwesort, Fleckenberg, Schmallenberg, Hochsauerlandkreis, North Rhine-Westphalia, Germany", "class": "waterway", "type": "stream", "importance": 0.3100099999999999, "geojson": {"type": "LineString", "coordinates": [[8.2528377, 51.1187472], [8.2523419, 51.118864], [8.2519386, 51.1190278], [8.2515985, 51.1192562], [8.2511715, 51.1195242], [8.2509738, 51.1197327], [8.2507602, 51.1200256], [8.2506258, 51.120254], [8.2504281, 51.1206511], [8.2501196, 51.1208298], [8.2497163, 51.1210482], [8.2492576, 51.1212071], [8.2491926, 51.1212346], [8.2485537, 51.1215049], [8.2481425, 51.1216985], [8.2478657, 51.1219467], [8.2475256, 51.1223736], [8.2471697, 51.1227459], [8.2468059, 51.1229941], [8.2466319, 51.123143], [8.2465449, 51.1233018], [8.2463314, 51.1235252], [8.2459281, 51.1238429], [8.2456117, 51.1240563], [8.2453587, 51.1242747], [8.245153, 51.1244336], [8.2449079, 51.1245775], [8.2445994, 51.1247016], [8.244291, 51.1248505], [8.2439509, 51.1249647], [8.243682, 51.1249696], [8.2434764, 51.1249051], [8.2432392, 51.1248902], [8.2430098, 51.1249597], [8.2427172, 51.1250342], [8.2424395, 51.1251194], [8.2421003, 51.1253121], [8.2417998, 51.125471], [8.241436, 51.1255851], [8.2408428, 51.1257737], [8.2403762, 51.1259425], [8.2401311, 51.1260865], [8.2400364, 51.1261323]]}}, {"place_id": 352420710, "licence": "Data \u00a9 OpenStreetMap contributors, ODbL 1.0. https://osm.org/copyright", "osm_type": "way", "osm_id": 1126158502, "boundingbox": ["51.1141403", "51.1144225", "8.2547852", "8.2548018"], "lat": "51.1141403", "lon": "8.2548018", "display_name": "Uentrop, Wulwesort, Schmallenberg, Hochsauerlandkreis, North Rhine-Westphalia, Germany", "class": "waterway", "type": "stream", "importance": 0.3100099999999999, "geojson": {"type": "LineString", "coordinates": [[8.2548018, 51.1141403], [8.2547852, 51.1144225]]}}, {"place_id": 352420711, "licence": "Data \u00a9 OpenStreetMap contributors, ODbL 1.0. https://osm.org/copyright", "osm_type": "way", "osm_id": 1126158503, "boundingbox": ["51.1090984", "51.1141403", "8.2548018", "8.259119"], "lat": "51.1112", "lon": "8.2566733", "display_name": "Uentrop, Wulwesort, Schmallenberg, Hochsauerlandkreis, North Rhine-Westphalia, Germany", "class": "waterway", "type": "stream", "importance": 0.3100099999999999, "geojson": {"type": "LineString", "coordinates": [[8.259119, 51.1091649], [8.2589558, 51.1091405], [8.2585093, 51.1090984], [8.2582022, 51.1091228], [8.2578671, 51.1091687], [8.2577408, 51.1092415], [8.2572312, 51.1096642], [8.2569737, 51.1099741], [8.2570381, 51.1106072], [8.2568879, 51.1109171], [8.2566733, 51.1112], [8.2564587, 51.1114963], [8.2563729, 51.1117658], [8.2554717, 51.1128704], [8.2553472, 51.11312], [8.2553472, 51.1137704], [8.2550941, 51.1138647], [8.2548727, 51.1139838], [8.2548018, 51.1141403]]}}, {"place_id": 276792663, "licence": "Data \u00a9 OpenStreetMap contributors, ODbL 1.0. https://osm.org/copyright", "osm_type": "way", "osm_id": 911972036, "boundingbox": ["51.1326524", "51.1327599", "8.2206526", "8.2206887"], "lat": "51.1327599", "lon": "8.2206526", "display_name": "Uentrop, Lenne, Schmallenberg, Hochsauerlandkreis, North Rhine-Westphalia, Germany", "class": "waterway", "type": "stream", "importance": 0.3100099999999999, "geojson": {"type": "LineString", "coordinates": [[8.2206887, 51.1326524], [8.2206526, 51.1327599]]}}, {"place_id": 277156577, "licence": "Data \u00a9 OpenStreetMap contributors, ODbL 1.0. https://osm.org/copyright", "osm_type": "way", "osm_id": 914634347, "boundingbox": ["51.1309254", "51.1309426", "8.222876", "8.2231781"], "lat": "51.1309426", "lon": "8.222876", "display_name": "Uentrop, Lenne, Schmallenberg, Hochsauerlandkreis, North Rhine-Westphalia, Germany", "class": "waterway", "type": "stream", "importance": 0.3100099999999999, "geojson": {"type": "LineString", "coordinates": [[8.2231781, 51.1309254], [8.222876, 51.1309426]]}}, {"place_id": 266892918, "licence": "Data \u00a9 OpenStreetMap contributors, ODbL 1.0. https://osm.org/copyright", "osm_type": "way", "osm_id": 833020756, "boundingbox": ["51.1261323", "51.1261878", "8.2399318", "8.2400364"], "lat": "51.1261323", "lon": "8.2400364", "display_name": "Uentrop, Lenne, Schmallenberg, Hochsauerlandkreis, North Rhine-Westphalia, Germany", "class": "waterway", "type": "stream", "importance": 0.3100099999999999, "geojson": {"type": "LineString", "coordinates": [[8.2400364, 51.1261323], [8.2399318, 51.1261878]]}}, {"place_id": 267486938, "licence": "Data \u00a9 OpenStreetMap contributors, ODbL 1.0. https://osm.org/copyright", "osm_type": "way", "osm_id": 833020757, "boundingbox": ["51.1144225", "51.1187147", "8.2529245", "8.2547857"], "lat": "51.1167045", "lon": "8.2547145", "display_name": "Uentrop, Wulwesort, Schmallenberg, Hochsauerlandkreis, North Rhine-Westphalia, Germany", "class": "waterway", "type": "stream", "importance": 0.3100099999999999, "geojson": {"type": "LineString", "coordinates": [[8.2547852, 51.1144225], [8.2547699, 51.114813], [8.2546937, 51.1149155], [8.2546592, 51.1149619], [8.2544931, 51.1150959], [8.2546433, 51.1152647], [8.2546987, 51.1153442], [8.2546671, 51.1154584], [8.2546592, 51.1156123], [8.2547224, 51.115791], [8.2547145, 51.1159797], [8.2547017, 51.116091], [8.2547857, 51.1164016], [8.2547145, 51.1167045], [8.254588, 51.1171761], [8.2544852, 51.1175038], [8.2544456, 51.1176825], [8.2543603, 51.1177479], [8.2543033, 51.1177917], [8.2541056, 51.1178165], [8.2540028, 51.1179506], [8.2540028, 51.1180498], [8.2540265, 51.118169], [8.2539158, 51.1182782], [8.2536785, 51.1183427], [8.2534808, 51.1183973], [8.2530537, 51.1186704], [8.2529245, 51.1187147]]}}, {"place_id": 277377584, "licence": "Data \u00a9 OpenStreetMap contributors, ODbL 1.0. https://osm.org/copyright", "osm_type": "way", "osm_id": 914634348, "boundingbox": ["51.1308547", "51.1309326", "8.2231781", "8.2245683"], "lat": "51.1308547", "lon": "8.223803", "display_name": "Uentrop, Lenne, Schmallenberg, Hochsauerlandkreis, North Rhine-Westphalia, Germany", "class": "waterway", "type": "stream", "importance": 0.3100099999999999, "geojson": {"type": "LineString", "coordinates": [[8.2245683, 51.1309165], [8.224036, 51.1308635], [8.223803, 51.1308547], [8.2235945, 51.1309326], [8.2233799, 51.1309291], [8.2232693, 51.1309195], [8.2231781, 51.1309254]]}}, {"place_id": 277253875, "licence": "Data \u00a9 OpenStreetMap contributors, ODbL 1.0. https://osm.org/copyright", "osm_type": "way", "osm_id": 911972035, "boundingbox": ["51.1327599", "51.1331729", "8.2206288", "8.2206526"], "lat": "51.1330261", "lon": "8.2206474", "display_name": "Uentrop, Lenne, Schmallenberg, Hochsauerlandkreis, North Rhine-Westphalia, Germany", "class": "waterway", "type": "stream", "importance": 0.3100099999999999, "geojson": {"type": "LineString", "coordinates": [[8.2206526, 51.1327599], [8.2206474, 51.1330261], [8.2206288, 51.1331729]]}}, {"place_id": 277402905, "licence": "Data \u00a9 OpenStreetMap contributors, ODbL 1.0. https://osm.org/copyright", "osm_type": "way", "osm_id": 914634350, "boundingbox": ["51.1309426", "51.1326524", "8.2206887", "8.222876"], "lat": "51.1315019", "lon": "8.2216316", "display_name": "Uentrop, Lenne, Schmallenberg, Hochsauerlandkreis, North Rhine-Westphalia, Germany", "class": "waterway", "type": "stream", "importance": 0.3100099999999999, "geojson": {"type": "LineString", "coordinates": [[8.222876, 51.1309426], [8.2225916, 51.1309628], [8.2225012, 51.1310358], [8.222338, 51.1310835], [8.2222437, 51.1311332], [8.2222097, 51.1313031], [8.2220786, 51.1313817], [8.2219591, 51.1314037], [8.22179, 51.1314091], [8.2216868, 51.131446], [8.2216316, 51.1315019], [8.2215446, 51.1315385], [8.2214083, 51.1316227], [8.2212594, 51.1317594], [8.2213003, 51.1318335], [8.2214577, 51.1319616], [8.2215218, 51.1320841], [8.2214111, 51.1321463], [8.2212158, 51.1322762], [8.2211079, 51.1323713], [8.2208882, 51.1324832], [8.2207846, 51.1325606], [8.2206887, 51.1326524]]}}, {"place_id": 278709445, "licence": "Data \u00a9 OpenStreetMap contributors, ODbL 1.0. https://osm.org/copyright", "osm_type": "way", "osm_id": 914634349, "boundingbox": ["51.1308371", "51.1309165", "8.2245683", "8.225179"], "lat": "51.1309165", "lon": "8.2245683", "display_name": "Uentrop, Lenne, Schmallenberg, Hochsauerlandkreis, North Rhine-Westphalia, Germany", "class": "waterway", "type": "stream", "importance": 0.3100099999999999, "geojson": {"type": "LineString", "coordinates": [[8.225179, 51.1308371], [8.2245683, 51.1309165]]}}, {"place_id": 199979590, "licence": "Data \u00a9 OpenStreetMap contributors, ODbL 1.0. https://osm.org/copyright", "osm_type": "way", "osm_id": 410469323, "boundingbox": ["51.1261878", "51.1306921", "8.2301352", "8.2399318"], "lat": "51.1281237", "lon": "8.234543", "display_name": "Uentrop, Lenne, Schmallenberg, Hochsauerlandkreis, North Rhine-Westphalia, Germany", "class": "waterway", "type": "stream", "importance": 0.3100099999999999, "geojson": {"type": "LineString", "coordinates": [[8.2399318, 51.1261878], [8.2397307, 51.1262804], [8.2397079, 51.1263191], [8.2397004, 51.1263577], [8.2394826, 51.1265133], [8.2393116, 51.1266789], [8.2390477, 51.1267711], [8.2387656, 51.1268196], [8.2383954, 51.1268962], [8.2380432, 51.1269153], [8.2376478, 51.1270047], [8.2372134, 51.1270043], [8.236863, 51.1269724], [8.2365801, 51.1271933], [8.2364061, 51.1272578], [8.2357722, 51.1274849], [8.2355849, 51.1275692], [8.2353977, 51.1277018], [8.234543, 51.1281237], [8.234399, 51.1282111], [8.2342886, 51.1283557], [8.234231, 51.1283979], [8.2340872, 51.1284021], [8.2338949, 51.1285305], [8.2336391, 51.1286329], [8.2334532, 51.1287534], [8.2332275, 51.1288378], [8.2329826, 51.1289945], [8.232757, 51.1291512], [8.2325169, 51.12935], [8.2322432, 51.1296001], [8.2320759, 51.1296699], [8.2318783, 51.1297478], [8.2316479, 51.1299768], [8.2313286, 51.1301215], [8.2310855, 51.1302147], [8.2306832, 51.130308], [8.2303509, 51.1305055], [8.2301352, 51.1306921]]}}, {"place_id": 355505436, "licence": "Data \u00a9 OpenStreetMap contributors, ODbL 1.0. https://osm.org/copyright", "osm_type": "way", "osm_id": 1137997580, "boundingbox": ["51.1306921", "51.1309079", "8.229902", "8.2301352"], "lat": "51.1306921", "lon": "8.2301352", "display_name": "Uentrop, Lenne, Schmallenberg, Hochsauerlandkreis, North Rhine-Westphalia, Germany", "class": "waterway", "type": "stream", "importance": 0.3100099999999999, "geojson": {"type": "LineString", "coordinates": [[8.2301352, 51.1306921], [8.229902, 51.1309079]]}}, {"place_id": 355505435, "licence": "Data \u00a9 OpenStreetMap contributors, ODbL 1.0. https://osm.org/copyright", "osm_type": "way", "osm_id": 1137997579, "boundingbox": ["51.130656", "51.1311165", "8.225179", "8.229902"], "lat": "51.1307195", "lon": "8.2276226", "display_name": "Uentrop, Lenne, Schmallenberg, Hochsauerlandkreis, North Rhine-Westphalia, Germany", "class": "waterway", "type": "stream", "importance": 0.3100099999999999, "geojson": {"type": "LineString", "coordinates": [[8.229902, 51.1309079], [8.2298088, 51.1309775], [8.2297038, 51.1310525], [8.2296076, 51.1310927], [8.2295231, 51.1311165], [8.2290072, 51.1310067], [8.2287682, 51.1309976], [8.2285845, 51.1309884], [8.2285204, 51.1310104], [8.2282726, 51.1309555], [8.2281677, 51.1308787], [8.2280394, 51.1308275], [8.2278966, 51.1307854], [8.2276226, 51.1307195], [8.2272903, 51.1306683], [8.2270222, 51.1306573], [8.2268065, 51.130672], [8.2266397, 51.130656], [8.2264939, 51.1306722], [8.2263142, 51.1307201], [8.2260729, 51.1308141], [8.2257222, 51.1308539], [8.2255414, 51.1308622], [8.2253196, 51.1308547], [8.225179, 51.1308371]]}}, {"place_id": 343148670, "licence": "Data \u00a9 OpenStreetMap contributors, ODbL 1.0. https://osm.org/copyright", "osm_type": "way", "osm_id": 1094334660, "boundingbox": ["51.1187147", "51.1187472", "8.2528377", "8.2529245"], "lat": "51.1187472", "lon": "8.2528377", "display_name": "Uentrop, Wulwesort, Schmallenberg, Hochsauerlandkreis, North Rhine-Westphalia, Germany", "class": "waterway", "type": "stream", "importance": 0.3100099999999999, "geojson": {"type": "LineString", "coordinates": [[8.2529245, 51.1187147], [8.2528377, 51.1187472]]}}]