[{"place_id": 298222807, "licence": "Data \u00a9 OpenStreetMap contributors, ODbL 1.0. https://osm.org/copyright", "osm_type": "relation", "osm_id": 37908, "boundingbox": ["47.170662", "47.2017324", "14.7149127", "14.769765"], "lat": "47.1912045", "lon": "14.7549244", "display_name": "Zeltweg, Bezirk Murtal, Styria, 8740, Austria", "class": "boundary", "type": "administrative", "importance": 0.5338642580813467, "icon": "https://nominatim.openstreetmap.org/ui/mapicons/poi_boundary_administrative.p.20.png"}]