[{"place_id": 298313423, "licence": "Data \u00a9 OpenStreetMap contributors, ODbL 1.0. https://osm.org/copyright", "osm_type": "relation", "osm_id": 2709666, "boundingbox": ["50.9943346", "51.0477277", "18.3675851", "18.4537885"], "lat": "51.0281551", "lon": "18.4222682", "display_name": "Gorz\u00f3w \u015al\u0105ski, gmina Gorz\u00f3w \u015al\u0105ski, Olesno County, Opole Voivodeship, 46-310, Poland", "class": "boundary", "type": "administrative", "importance": 0.3801188395028131, "icon": "https://nominatim.openstreetmap.org/ui/mapicons/poi_boundary_administrative.p.20.png"}]