[{"place_id": 297570172, "licence": "Data \u00a9 OpenStreetMap contributors, ODbL 1.0. https://osm.org/copyright", "osm_type": "relation", "osm_id": 215977, "boundingbox": ["50.5733108", "50.6691606", "8.3897763", "8.484692"], "lat": "50.5927946", "lon": "8.4649082", "display_name": "A\u00dflar, Lahn-Dill-Kreis, Hesse, 35614, Germany", "class": "boundary", "type": "administrative", "importance": 0.4143318043498931, "icon": "https://nominatim.openstreetmap.org/ui/mapicons/poi_boundary_administrative.p.20.png"}]