[{"place_id": 24526289, "licence": "Data \u00a9 OpenStreetMap contributors, ODbL 1.0. https://osm.org/copyright", "osm_type": "node", "osm_id": 2690897664, "boundingbox": ["53.2359247", "53.2360247", "8.4609636", "8.4610636"], "lat": "53.2359747", "lon": "8.4610136", "display_name": "Polizei Elsfleth, 6a, Rittersweg, Elsfleth, Landkreis Wesermarsch, Lower Saxony, 26931, Germany", "class": "amenity", "type": "police", "importance": 0.21000999999999997, "icon": "https://nominatim.openstreetmap.org/ui/mapicons/amenity_police2.p.20.png"}]