[{"place_id": 298747823, "licence": "Data \u00a9 OpenStreetMap contributors, ODbL 1.0. https://osm.org/copyright", "osm_type": "relation", "osm_id": 8434337, "boundingbox": ["48.8980501", "48.9145224", "9.014309", "9.0383741"], "lat": "48.90655385", "lon": "9.025837957784162", "display_name": "Pulverdingen, Vaihingen an der Enz, VVG Vaihingen an der Enz, Landkreis Ludwigsburg, Baden-W\u00fcrttemberg, Germany", "class": "boundary", "type": "administrative", "importance": 0.41000000000000003, "icon": "https://nominatim.openstreetmap.org/ui/mapicons/poi_boundary_administrative.p.20.png"}]