{"version": 0.6, "generator": "Overpass API 0.7.59.4 36d058c8", "osm3s": {"timestamp_osm_base": "2023-03-07T10:53:49Z", "copyright": "The data included in this document is from www.openstreetmap.org. The data is made available under ODbL."}, "elements": [{"type": "node", "id": 5227057303, "lat": 49.5971484, "lon": 8.9910445}, {"type": "node", "id": 5227057304, "lat": 49.5971153, "lon": 8.991059}, {"type": "node", "id": 5227057305, "lat": 49.5971242, "lon": 8.9911075}, {"type": "node", "id": 5227057306, "lat": 49.5971573, "lon": 8.9910931}, {"type": "node", "id": 9605713441, "lat": 49.5971198, "lon": 8.9910832}, {"type": "way", "id": 540263289, "nodes": [5227057303, 5227057304, 9605713441, 5227057305, 5227057306, 5227057303], "tags": {"building": "transformer_tower", "level": "2", "power": "substation", "roof:colour": "red", "roof:shape": "gabled", "substation": "minor_distribution", "voltage": "20000"}}]}