[{"place_id": 309671702, "licence": "Data \u00a9 OpenStreetMap contributors, ODbL 1.0. https://osm.org/copyright", "osm_type": "relation", "osm_id": 13775247, "boundingbox": ["51.2489103", "51.2841057", "9.4901887", "9.5171748"], "lat": "51.2684595", "lon": "9.5007979", "display_name": "Bergshausen, Fuldabr\u00fcck, Landkreis Kassel, Hesse, Germany", "class": "boundary", "type": "administrative", "importance": 0.38500999999999996, "icon": "https://nominatim.openstreetmap.org/ui/mapicons/poi_boundary_administrative.p.20.png"}]