[{"place_id": 307525384, "licence": "Data \u00a9 OpenStreetMap contributors, ODbL 1.0. https://osm.org/copyright", "osm_type": "relation", "osm_id": 7417, "boundingbox": ["46.3471572", "47.277335", "0.8671135", "2.2045337"], "lat": "46.81210565", "lon": "1.5382051557056249", "display_name": "Indre, Centre-Val de Loire, Metropolitan France, France", "class": "boundary", "type": "administrative", "importance": 0.5910426101581934, "icon": "https://nominatim.openstreetmap.org/ui/mapicons/poi_boundary_administrative.p.20.png"}]